<annotation>
	<folder>train</folder>
	<filename>car5.jpeg</filename>
	<path>C:\Users\oknor\Documents\Programming\TrainingModels\TensorFlow\workspace\car_training\images\train\car5.jpeg</path>
	<source>
		<database>Unknown</database>
	</source>
	<size>
		<width>1920</width>
		<height>1080</height>
		<depth>3</depth>
	</size>
	<segmented>0</segmented>
	<object>
		<name>car</name>
		<pose>Unspecified</pose>
		<truncated>0</truncated>
		<difficult>0</difficult>
		<bndbox>
			<xmin>787</xmin>
			<ymin>316</ymin>
			<xmax>1626</xmax>
			<ymax>1004</ymax>
		</bndbox>
	</object>
</annotation>
